{
  "changelogDate": "20221204155349",
  "dto": "mapstruct",
  "fields": [
    {
      "fieldName": "name",
      "fieldType": "String",
      "fieldValidateRules": ["required"]
    },
    {
      "fieldName": "phone",
      "fieldType": "String",
      "fieldValidateRules": ["required"]
    },
    {
      "fieldName": "address",
      "fieldType": "String",
      "fieldValidateRules": ["required"]
    },
    {
      "fieldName": "photo",
      "fieldType": "byte[]",
      "fieldTypeBlobContent": "image",
      "fieldValidateRules": ["required"]
    },
    {
      "fieldName": "longitude",
      "fieldType": "BigDecimal"
    },
    {
      "fieldName": "latitude",
      "fieldType": "BigDecimal"
    }
  ],
  "name": "Restaurant",
  "pagination": "no",
  "readOnly": false,
  "relationships": [],
  "service": "serviceClass"
}
